{
    "EpisodeId": 2000702,
    "StoryType": 2,
    "Order": 2,
    "Prev": 2000701,
    "Next": 2000703,
    "Chapter": "FAIR IS FOUL, AND FOUL IS FAIR",
    "Title": "一緒の舞台に",
    "EpisodeDetail": [
        {
            "Id": 2000702001,
            "EpisodeMasterId": 2000702,
            "Order": 1,
            "GroupOrder": 1,
            "SpeakerName": "栞",
            "FontSize": 2,
            "Phrase": "暦ちゃん、千秋楽お疲れ様ーっ！/n大成功だったね！　",
            "BackgroundImageFileName": "700",
            "BgmFileName": "10",
            "VoiceFileName": "20007020010",
            "CharacterMotions": [
                {
                    "slotNumber": 1,
                    "FacialExpressionMasterId": 200,
                    "BodyMotionMasterId": 2,
                    "LipSyncMasterId": 2,
                    "SpineId": 50903,
                    "CharacterAppearanceType": 0,
                    "CharacterPosition": 3,
                    "CharacterLayerType": 1,
                    "SpineSize": 2
                }
            ],
            "SpeakerIconId": "509"
        },
        {
            "Id": 2000702002,
            "EpisodeMasterId": 2000702,
            "Order": 1,
            "GroupOrder": 2,
            "SpeakerName": "暦",
            "FontSize": 2,
            "Phrase": "寮に呼び出されて何の用かと思いましたわ。/nまさかお祝いしてくれるだなんて。",
            "VoiceFileName": "20007020020",
            "CharacterMotions": [
                {
                    "slotNumber": 1,
                    "FacialExpressionMasterId": 105,
                    "BodyMotionMasterId": 11,
                    "LipSyncMasterId": 1,
                    "SpineId": 30119,
                    "CharacterAppearanceType": 0,
                    "CharacterPosition": 3,
                    "CharacterLayerType": 1,
                    "SpineSize": 2
                }
            ],
            "SpeakerIconId": "301"
        },
        {
            "Id": 2000702003,
            "EpisodeMasterId": 2000702,
            "Order": 1,
            "GroupOrder": 3,
            "SpeakerName": "栞",
            "FontSize": 2,
            "Phrase": "ありゃ、こういうの初めて？　打ち上げとか無いみたいだから、/n暦ちゃん頑張ってるし何かしたいなーって。",
            "VoiceFileName": "20007020030",
            "CharacterMotions": [
                {
                    "slotNumber": 1,
                    "SpineId": 0,
                    "CharacterAppearanceType": 0,
                    "CharacterPosition": 2,
                    "CharacterLayerType": 1,
                    "SpineSize": 2
                },
                {
                    "slotNumber": 2,
                    "FacialExpressionMasterId": 500,
                    "BodyMotionMasterId": 7,
                    "LipSyncMasterId": 1,
                    "SpineId": 50903,
                    "CharacterAppearanceType": 0,
                    "CharacterPosition": 4,
                    "CharacterLayerType": 1,
                    "SpineSize": 2
                }
            ],
            "SpeakerIconId": "509"
        },
        {
            "Id": 2000702004,
            "EpisodeMasterId": 2000702,
            "Order": 1,
            "GroupOrder": 4,
            "SpeakerName": "暦",
            "FontSize": 2,
            "Phrase": "稽古以外で皆さんと関わる機会も少なかったですし……。",
            "VoiceFileName": "20007020040",
            "CharacterMotions": [
                {
                    "slotNumber": 1,
                    "FacialExpressionMasterId": 102,
                    "BodyMotionMasterId": 13,
                    "LipSyncMasterId": 4,
                    "SpineId": 0,
                    "CharacterAppearanceType": 0,
                    "CharacterPosition": 2,
                    "CharacterLayerType": 1,
                    "SpineSize": 2
                },
                {
                    "slotNumber": 2,
                    "SpineId": 0,
                    "CharacterAppearanceType": 0,
                    "CharacterPosition": 4,
                    "CharacterLayerType": 1,
                    "SpineSize": 2
                }
            ],
            "SpeakerIconId": "301"
        },
        {
            "Id": 2000702005,
            "EpisodeMasterId": 2000702,
            "Order": 2,
            "GroupOrder": 4,
            "SpeakerName": "暦",
            "FontSize": 2,
            "Phrase": "こんなに気軽に声をかけてくるのは、あなたくらいのものですわ。",
            "VoiceFileName": "20007020041",
            "CharacterMotions": [
                {
                    "slotNumber": 1,
                    "FacialExpressionMasterId": 105,
                    "BodyMotionMasterId": 3,
                    "LipSyncMasterId": 1,
                    "SpineId": 0,
                    "CharacterAppearanceType": 0,
                    "CharacterPosition": 2,
                    "CharacterLayerType": 1,
                    "SpineSize": 2
                },
                {
                    "slotNumber": 2,
                    "SpineId": 0,
                    "CharacterAppearanceType": 0,
                    "CharacterPosition": 4,
                    "CharacterLayerType": 1,
                    "SpineSize": 2
                }
            ],
            "SpeakerIconId": "301"
        },
        {
            "Id": 2000702006,
            "EpisodeMasterId": 2000702,
            "Order": 1,
            "GroupOrder": 5,
            "SpeakerName": "栞",
            "FontSize": 2,
            "Phrase": "そお？　暦ちゃんは努力家だもんね。",
            "VoiceFileName": "20007020050",
            "CharacterMotions": [
                {
                    "slotNumber": 1,
                    "SpineId": 0,
                    "CharacterAppearanceType": 0,
                    "CharacterPosition": 2,
                    "CharacterLayerType": 1,
                    "SpineSize": 2
                },
                {
                    "slotNumber": 2,
                    "FacialExpressionMasterId": 201,
                    "BodyMotionMasterId": 17,
                    "LipSyncMasterId": 1,
                    "SpineId": 0,
                    "CharacterAppearanceType": 0,
                    "CharacterPosition": 4,
                    "CharacterLayerType": 1,
                    "SpineSize": 2
                }
            ],
            "SpeakerIconId": "509"
        },
        {
            "Id": 2000702007,
            "EpisodeMasterId": 2000702,
            "Order": 2,
            "GroupOrder": 5,
            "SpeakerName": "栞",
            "FontSize": 2,
            "Phrase": "じゃあ今日は、私が沢山ねぎらっちゃう！",
            "VoiceFileName": "20007020051",
            "CharacterMotions": [
                {
                    "slotNumber": 1,
                    "SpineId": 0,
                    "CharacterAppearanceType": 0,
                    "CharacterPosition": 2,
                    "CharacterLayerType": 1,
                    "SpineSize": 2
                },
                {
                    "slotNumber": 2,
                    "FacialExpressionMasterId": 101,
                    "BodyMotionMasterId": 2,
                    "LipSyncMasterId": 1,
                    "SpineId": 0,
                    "CharacterAppearanceType": 0,
                    "CharacterPosition": 4,
                    "CharacterLayerType": 1,
                    "SpineSize": 2
                }
            ],
            "SpeakerIconId": "509"
        },
        {
            "Id": 2000702008,
            "EpisodeMasterId": 2000702,
            "Order": 1,
            "GroupOrder": 6,
            "SpeakerName": "暦",
            "FontSize": 2,
            "Phrase": "ふふ、ありがとうございます。",
            "VoiceFileName": "20007020060",
            "CharacterMotions": [
                {
                    "slotNumber": 1,
                    "FacialExpressionMasterId": 200,
                    "BodyMotionMasterId": 4,
                    "LipSyncMasterId": 1,
                    "SpineId": 0,
                    "CharacterAppearanceType": 0,
                    "CharacterPosition": 2,
                    "CharacterLayerType": 1,
                    "SpineSize": 2
                },
                {
                    "slotNumber": 2,
                    "SpineId": 0,
                    "CharacterAppearanceType": 0,
                    "CharacterPosition": 4,
                    "CharacterLayerType": 1,
                    "SpineSize": 2
                }
            ],
            "SpeakerIconId": "301"
        },
        {
            "Id": 2000702009,
            "EpisodeMasterId": 2000702,
            "Order": 1,
            "GroupOrder": 7,
            "SpeakerName": "暦",
            "FontSize": 2,
            "Phrase": "ところで栞さん、明日のオーディションの準備は順調ですの？",
            "VoiceFileName": "20007020070",
            "CharacterMotions": [
                {
                    "slotNumber": 1,
                    "FacialExpressionMasterId": 100,
                    "BodyMotionMasterId": 3,
                    "LipSyncMasterId": 1,
                    "SpineId": 0,
                    "CharacterAppearanceType": 0,
                    "CharacterPosition": 2,
                    "CharacterLayerType": 1,
                    "SpineSize": 2
                },
                {
                    "slotNumber": 2,
                    "SpineId": 0,
                    "CharacterAppearanceType": 0,
                    "CharacterPosition": 4,
                    "CharacterLayerType": 1,
                    "SpineSize": 2
                }
            ],
            "SpeakerIconId": "301"
        },
        {
            "Id": 2000702010,
            "EpisodeMasterId": 2000702,
            "Order": 1,
            "GroupOrder": 8,
            "SpeakerName": "暦",
            "FontSize": 2,
            "Phrase": "いつか共演したいと私が伝えた時、/n約束してくださったじゃないですか。次こそは舞台に立つって。",
            "VoiceFileName": "20007020080",
            "CharacterMotions": [
                {
                    "slotNumber": 1,
                    "FacialExpressionMasterId": 105,
                    "BodyMotionMasterId": 14,
                    "LipSyncMasterId": 1,
                    "SpineId": 0,
                    "CharacterAppearanceType": 0,
                    "CharacterPosition": 2,
                    "CharacterLayerType": 1,
                    "SpineSize": 2
                },
                {
                    "slotNumber": 2,
                    "SpineId": 0,
                    "CharacterAppearanceType": 0,
                    "CharacterPosition": 4,
                    "CharacterLayerType": 1,
                    "SpineSize": 2
                }
            ],
            "SpeakerIconId": "301"
        },
        {
            "Id": 2000702011,
            "EpisodeMasterId": 2000702,
            "Order": 1,
            "GroupOrder": 9,
            "SpeakerName": "栞",
            "FontSize": 2,
            "Phrase": "まさに今頑張ってるよ！　しばらく役を貰えなくて、/nブランクある身だけどね……。",
            "VoiceFileName": "20007020090",
            "CharacterMotions": [
                {
                    "slotNumber": 1,
                    "SpineId": 0,
                    "CharacterAppearanceType": 0,
                    "CharacterPosition": 2,
                    "CharacterLayerType": 1,
                    "SpineSize": 2
                },
                {
                    "slotNumber": 2,
                    "FacialExpressionMasterId": 105,
                    "BodyMotionMasterId": 21,
                    "LipSyncMasterId": 1,
                    "SpineId": 0,
                    "CharacterAppearanceType": 0,
                    "CharacterPosition": 4,
                    "CharacterLayerType": 1,
                    "SpineSize": 2
                }
            ],
            "SpeakerIconId": "509"
        },
        {
            "Id": 2000702012,
            "EpisodeMasterId": 2000702,
            "Order": 1,
            "GroupOrder": 10,
            "SpeakerName": "栞",
            "FontSize": 2,
            "Phrase": "暦ちゃんの舞台を観て、私も負けてられないって思った。/n主役には暦ちゃんがなったとしても、脇役として……支えたい。",
            "VoiceFileName": "20007020100",
            "CharacterMotions": [
                {
                    "slotNumber": 1,
                    "SpineId": 0,
                    "CharacterAppearanceType": 0,
                    "CharacterPosition": 2,
                    "CharacterLayerType": 1,
                    "SpineSize": 2
                },
                {
                    "slotNumber": 2,
                    "FacialExpressionMasterId": 70,
                    "BodyMotionMasterId": 7,
                    "LipSyncMasterId": 4,
                    "SpineId": 0,
                    "CharacterAppearanceType": 0,
                    "CharacterPosition": 4,
                    "CharacterLayerType": 1,
                    "SpineSize": 2
                }
            ],
            "SpeakerIconId": "509"
        },
        {
            "Id": 2000702013,
            "EpisodeMasterId": 2000702,
            "Order": 1,
            "GroupOrder": 11,
            "SpeakerName": "栞",
            "FontSize": 2,
            "Phrase": "ううん、端役でもいい。/n今度こそ舞台に立つよ！",
            "VoiceFileName": "20007020110",
            "CharacterMotions": [
                {
                    "slotNumber": 1,
                    "SpineId": 0,
                    "CharacterAppearanceType": 0,
                    "CharacterPosition": 2,
                    "CharacterLayerType": 1,
                    "SpineSize": 2
                },
                {
                    "slotNumber": 2,
                    "FacialExpressionMasterId": 100,
                    "HeadMotionMasterId": 2,
                    "BodyMotionMasterId": 17,
                    "LipSyncMasterId": 1,
                    "SpineId": 0,
                    "CharacterAppearanceType": 0,
                    "CharacterPosition": 4,
                    "CharacterLayerType": 1,
                    "SpineSize": 2
                }
            ],
            "SpeakerIconId": "509"
        },
        {
            "Id": 2000702014,
            "EpisodeMasterId": 2000702,
            "Order": 1,
            "GroupOrder": 12,
            "SpeakerName": "暦",
            "FontSize": 2,
            "Phrase": "もうっ、そんなに卑屈にならないでくださいな！/nせっかくなら、私と主役を争う気で挑まれたらどうですの？",
            "VoiceFileName": "20007020120",
            "CharacterMotions": [
                {
                    "slotNumber": 1,
                    "FacialExpressionMasterId": 110,
                    "BodyMotionMasterId": 3,
                    "LipSyncMasterId": 4,
                    "SpineId": 0,
                    "CharacterAppearanceType": 0,
                    "CharacterPosition": 2,
                    "CharacterLayerType": 1,
                    "SpineSize": 2
                },
                {
                    "slotNumber": 2,
                    "SpineId": 0,
                    "CharacterAppearanceType": 0,
                    "CharacterPosition": 4,
                    "CharacterLayerType": 1,
                    "SpineSize": 2
                }
            ],
            "SpeakerIconId": "301"
        },
        {
            "Id": 2000702015,
            "EpisodeMasterId": 2000702,
            "Order": 1,
            "GroupOrder": 13,
            "SpeakerName": "栞",
            "FontSize": 2,
            "Phrase": "そ、そうだね！　暦ちゃんに負けず主役勝ち取るぞー！",
            "VoiceFileName": "20007020130",
            "CharacterMotions": [
                {
                    "slotNumber": 1,
                    "SpineId": 0,
                    "CharacterAppearanceType": 0,
                    "CharacterPosition": 2,
                    "CharacterLayerType": 1,
                    "SpineSize": 2
                },
                {
                    "slotNumber": 2,
                    "FacialExpressionMasterId": 201,
                    "BodyMotionMasterId": 8,
                    "LipSyncMasterId": 1,
                    "SpineId": 0,
                    "CharacterAppearanceType": 0,
                    "CharacterPosition": 4,
                    "CharacterLayerType": 1,
                    "SpineSize": 2
                }
            ],
            "SpeakerIconId": "509"
        },
        {
            "Id": 2000702016,
            "EpisodeMasterId": 2000702,
            "Order": 1,
            "GroupOrder": 14,
            "SpeakerName": "暦",
            "FontSize": 2,
            "Phrase": "その意気です！",
            "VoiceFileName": "20007020140",
            "CharacterMotions": [
                {
                    "slotNumber": 1,
                    "FacialExpressionMasterId": 200,
                    "BodyMotionMasterId": 2,
                    "LipSyncMasterId": 2,
                    "SpineId": 0,
                    "CharacterAppearanceType": 0,
                    "CharacterPosition": 2,
                    "CharacterLayerType": 1,
                    "SpineSize": 2
                },
                {
                    "slotNumber": 2,
                    "SpineId": 0,
                    "CharacterAppearanceType": 0,
                    "CharacterPosition": 4,
                    "CharacterLayerType": 1,
                    "SpineSize": 2
                }
            ],
            "SpeakerIconId": "301"
        },
        {
            "Id": 2000702017,
            "EpisodeMasterId": 2000702,
            "Order": 1,
            "GroupOrder": 15,
            "SpeakerName": "栞",
            "FontSize": 2,
            "Phrase": "よーし……やる気出て落ち着かなくなってきた。",
            "VoiceFileName": "20007020150",
            "CharacterMotions": [
                {
                    "slotNumber": 1,
                    "SpineId": 0,
                    "CharacterAppearanceType": 0,
                    "CharacterPosition": 2,
                    "CharacterLayerType": 1,
                    "SpineSize": 2
                },
                {
                    "slotNumber": 2,
                    "FacialExpressionMasterId": 101,
                    "BodyMotionMasterId": 20,
                    "LipSyncMasterId": 1,
                    "SpineId": 0,
                    "CharacterAppearanceType": 0,
                    "CharacterPosition": 4,
                    "CharacterLayerType": 1,
                    "SpineSize": 2
                }
            ],
            "SpeakerIconId": "509"
        },
        {
            "Id": 2000702018,
            "EpisodeMasterId": 2000702,
            "Order": 2,
            "GroupOrder": 15,
            "SpeakerName": "栞",
            "FontSize": 2,
            "Phrase": "ごめん、ちょっと台本取ってくる……！",
            "VoiceFileName": "20007020151",
            "CharacterMotions": [
                {
                    "slotNumber": 1,
                    "SpineId": 0,
                    "CharacterAppearanceType": 0,
                    "CharacterPosition": 2,
                    "CharacterLayerType": 1,
                    "SpineSize": 2
                },
                {
                    "slotNumber": 2,
                    "FacialExpressionMasterId": 201,
                    "BodyMotionMasterId": 4,
                    "LipSyncMasterId": 1,
                    "SpineId": 0,
                    "CharacterAppearanceType": 0,
                    "CharacterPosition": 4,
                    "CharacterLayerType": 1,
                    "SpineSize": 2
                }
            ],
            "SpeakerIconId": "509"
        },
        {
            "Id": 2000702019,
            "EpisodeMasterId": 2000702,
            "Order": 1,
            "GroupOrder": 16,
            "FontSize": 2,
            "Phrase": "",
            "CharacterMotions": []
        },
        {
            "Id": 2000702020,
            "EpisodeMasterId": 2000702,
            "Order": 1,
            "GroupOrder": 17,
            "SpeakerName": "暦",
            "FontSize": 2,
            "Phrase": "（周りに流されず練習に励むこと、/n　更なる成長を求めろ。現状に甘んじるな）",
            "VoiceFileName": "20007020160",
            "CharacterMotions": [
                {
                    "slotNumber": 1,
                    "FacialExpressionMasterId": 402,
                    "BodyMotionMasterId": 7,
                    "SpineId": 30119,
                    "CharacterAppearanceType": 0,
                    "CharacterPosition": 3,
                    "CharacterLayerType": 1,
                    "SpineSize": 2
                }
            ],
            "SpeakerIconId": "301"
        },
        {
            "Id": 2000702021,
            "EpisodeMasterId": 2000702,
            "Order": 1,
            "GroupOrder": 18,
            "SpeakerName": "暦",
            "FontSize": 2,
            "Phrase": "（両親の教えにしたがうなら、/n　誰かに深入りすべきではありません。ですが）",
            "VoiceFileName": "20007020170",
            "CharacterMotions": [
                {
                    "slotNumber": 1,
                    "FacialExpressionMasterId": 73,
                    "HeadMotionMasterId": 2,
                    "BodyMotionMasterId": 25,
                    "SpineId": 0,
                    "CharacterAppearanceType": 0,
                    "CharacterPosition": 3,
                    "CharacterLayerType": 1,
                    "SpineSize": 2
                }
            ],
            "SpeakerIconId": "301"
        },
        {
            "Id": 2000702022,
            "EpisodeMasterId": 2000702,
            "Order": 1,
            "GroupOrder": 19,
            "SpeakerName": "暦",
            "FontSize": 2,
            "Phrase": "（……優しいあの人と、一緒に舞台を演じられますように）",
            "VoiceFileName": "20007020180",
            "CharacterMotions": [
                {
                    "slotNumber": 1,
                    "FacialExpressionMasterId": 74,
                    "BodyMotionMasterId": 4,
                    "SpineId": 0,
                    "CharacterAppearanceType": 0,
                    "CharacterPosition": 3,
                    "CharacterLayerType": 1,
                    "SpineSize": 2
                }
            ],
            "SpeakerIconId": "301"
        },
        {
            "Id": 2000702023,
            "EpisodeMasterId": 2000702,
            "Order": 1,
            "GroupOrder": 20,
            "FontSize": 2,
            "Phrase": "",
            "BackgroundImageFileName": "1050",
            "BackgroundImageFileFadeType": 1,
            "BgmFileName": "999",
            "CharacterMotions": [],
            "FadeValue1": 0.30000001192092896,
            "FadeValue2": 0.10000000149011612,
            "FadeValue3": 0.30000001192092896
        },
        {
            "Id": 2000702024,
            "EpisodeMasterId": 2000702,
            "Order": 1,
            "GroupOrder": 21,
            "SpeakerName": "演出家",
            "FontSize": 2,
            "Phrase": "――ではこの後、次の公演の読み合わせを行う。/n先ほど名前を呼ばれたメンバーはこの場に残るように。",
            "VoiceFileName": "20007020190",
            "CharacterMotions": [],
            "SpeakerIconId": "1"
        },
        {
            "Id": 2000702025,
            "EpisodeMasterId": 2000702,
            "Order": 1,
            "GroupOrder": 22,
            "SpeakerName": "暦",
            "FontSize": 2,
            "Phrase": "次の公演の主役には、私が選ばれた。/nこれまでの功績を評価され、私の成長をうながすための主演だった。",
            "VoiceFileName": "20007020200",
            "CharacterMotions": [],
            "SpeakerIconId": "301"
        },
        {
            "Id": 2000702026,
            "EpisodeMasterId": 2000702,
            "Order": 1,
            "GroupOrder": 23,
            "SpeakerName": "暦",
            "FontSize": 2,
            "Phrase": "栞さんは望んでいた脇役にも、端役にもあてがわれず、/n彼女の名前が呼ばれることはなかった。",
            "VoiceFileName": "20007020210",
            "CharacterMotions": [],
            "SpeakerIconId": "301"
        },
        {
            "Id": 2000702027,
            "EpisodeMasterId": 2000702,
            "Order": 1,
            "GroupOrder": 24,
            "FontSize": 2,
            "Phrase": "",
            "BackgroundImageFileName": "670",
            "BackgroundImageFileFadeType": 1,
            "CharacterMotions": [],
            "FadeValue1": 0.30000001192092896,
            "FadeValue2": 0.10000000149011612,
            "FadeValue3": 0.30000001192092896
        },
        {
            "Id": 2000702028,
            "EpisodeMasterId": 2000702,
            "Order": 1,
            "GroupOrder": 25,
            "SpeakerName": "演出家",
            "FontSize": 2,
            "Phrase": "ではこれにて、本日の稽古を終了する。/n近々台本なしで稽古を行う、各自セリフを覚えてくるように。",
            "BgmFileName": "6",
            "VoiceFileName": "20007020220",
            "CharacterMotions": [],
            "SpeakerIconId": "1"
        },
        {
            "Id": 2000702029,
            "EpisodeMasterId": 2000702,
            "Order": 1,
            "GroupOrder": 26,
            "SpeakerName": "一同",
            "FontSize": 2,
            "Phrase": "はい！",
            "VoiceFileName": "20007020230",
            "CharacterMotions": [],
            "SpeakerIconId": "1"
        },
        {
            "Id": 2000702030,
            "EpisodeMasterId": 2000702,
            "Order": 1,
            "GroupOrder": 27,
            "SpeakerName": "暦",
            "FontSize": 2,
            "Phrase": "……。",
            "VoiceFileName": "20007020240",
            "CharacterMotions": [
                {
                    "slotNumber": 1,
                    "FacialExpressionMasterId": 400,
                    "BodyMotionMasterId": 25,
                    "SpineId": 30119,
                    "CharacterAppearanceType": 0,
                    "CharacterPosition": 3,
                    "CharacterLayerType": 1,
                    "SpineSize": 2
                }
            ],
            "SpeakerIconId": "301"
        },
        {
            "Id": 2000702031,
            "EpisodeMasterId": 2000702,
            "Order": 1,
            "GroupOrder": 28,
            "FontSize": 2,
            "Phrase": "",
            "BackgroundImageFileName": "690",
            "BackgroundImageFileFadeType": 1,
            "CharacterMotions": [],
            "FadeValue1": 0.30000001192092896,
            "FadeValue2": 0.10000000149011612,
            "FadeValue3": 0.30000001192092896
        },
        {
            "Id": 2000702032,
            "EpisodeMasterId": 2000702,
            "Order": 1,
            "GroupOrder": 29,
            "SpeakerName": "暦",
            "FontSize": 2,
            "Phrase": "スーツケースなんか持って、/n一体どこへ行かれるのです？",
            "VoiceFileName": "20007020250",
            "CharacterMotions": [
                {
                    "slotNumber": 1,
                    "FacialExpressionMasterId": 502,
                    "BodyMotionMasterId": 3,
                    "LipSyncMasterId": 4,
                    "SpineId": 30119,
                    "CharacterAppearanceType": 0,
                    "CharacterPosition": 3,
                    "CharacterLayerType": 1,
                    "SpineSize": 2
                }
            ],
            "SpeakerIconId": "301"
        },
        {
            "Id": 2000702033,
            "EpisodeMasterId": 2000702,
            "Order": 1,
            "GroupOrder": 30,
            "SpeakerName": "栞",
            "FontSize": 2,
            "Phrase": "びっくりした。",
            "VoiceFileName": "20007020260",
            "CharacterMotions": [
                {
                    "slotNumber": 1,
                    "SpineId": 0,
                    "CharacterAppearanceType": 0,
                    "CharacterPosition": 2,
                    "CharacterLayerType": 1,
                    "SpineSize": 2
                },
                {
                    "slotNumber": 2,
                    "FacialExpressionMasterId": 502,
                    "BodyMotionMasterId": 5,
                    "LipSyncMasterId": 4,
                    "SpineId": 50903,
                    "CharacterAppearanceType": 0,
                    "CharacterPosition": 4,
                    "CharacterLayerType": 1,
                    "SpineSize": 2
                }
            ],
            "SpeakerIconId": "509"
        },
        {
            "Id": 2000702034,
            "EpisodeMasterId": 2000702,
            "Order": 2,
            "GroupOrder": 30,
            "SpeakerName": "栞",
            "FontSize": 2,
            "Phrase": "……タイミングいいなあ。まさか暦ちゃんの方から来てくれるなんて。",
            "VoiceFileName": "20007020261",
            "CharacterMotions": [
                {
                    "slotNumber": 1,
                    "SpineId": 0,
                    "CharacterAppearanceType": 0,
                    "CharacterPosition": 2,
                    "CharacterLayerType": 1,
                    "SpineSize": 2
                },
                {
                    "slotNumber": 2,
                    "FacialExpressionMasterId": 402,
                    "BodyMotionMasterId": 4,
                    "LipSyncMasterId": 1,
                    "SpineId": 0,
                    "CharacterAppearanceType": 0,
                    "CharacterPosition": 4,
                    "CharacterLayerType": 1,
                    "SpineSize": 2
                }
            ],
            "SpeakerIconId": "509"
        },
        {
            "Id": 2000702035,
            "EpisodeMasterId": 2000702,
            "Order": 1,
            "GroupOrder": 31,
            "SpeakerName": "暦",
            "FontSize": 2,
            "Phrase": "連絡がつかないので会いに来ました。",
            "VoiceFileName": "20007020270",
            "CharacterMotions": [
                {
                    "slotNumber": 1,
                    "FacialExpressionMasterId": 400,
                    "BodyMotionMasterId": 25,
                    "LipSyncMasterId": 4,
                    "SpineId": 0,
                    "CharacterAppearanceType": 0,
                    "CharacterPosition": 2,
                    "CharacterLayerType": 1,
                    "SpineSize": 2
                },
                {
                    "slotNumber": 2,
                    "SpineId": 0,
                    "CharacterAppearanceType": 0,
                    "CharacterPosition": 4,
                    "CharacterLayerType": 1,
                    "SpineSize": 2
                }
            ],
            "SpeakerIconId": "301"
        },
        {
            "Id": 2000702036,
            "EpisodeMasterId": 2000702,
            "Order": 1,
            "GroupOrder": 32,
            "SpeakerName": "暦",
            "FontSize": 2,
            "Phrase": "まさか……今回もダメだったから、/n銀河座を辞めるなんて言いませんわよね？　",
            "VoiceFileName": "20007020280",
            "CharacterMotions": [
                {
                    "slotNumber": 1,
                    "HeadMotionMasterId": 2,
                    "BodyMotionMasterId": 11,
                    "LipSyncMasterId": 4,
                    "SpineId": 0,
                    "CharacterAppearanceType": 0,
                    "CharacterPosition": 2,
                    "CharacterLayerType": 1,
                    "SpineSize": 2
                },
                {
                    "slotNumber": 2,
                    "SpineId": 0,
                    "CharacterAppearanceType": 0,
                    "CharacterPosition": 4,
                    "CharacterLayerType": 1,
                    "SpineSize": 2
                }
            ],
            "SpeakerIconId": "301"
        },
        {
            "Id": 2000702037,
            "EpisodeMasterId": 2000702,
            "Order": 1,
            "GroupOrder": 33,
            "SpeakerName": "栞",
            "FontSize": 2,
            "Phrase": "違うの。実はね、お父さんが倒れて……。/n実家のお店を手伝わなきゃいけなくなったんだ。",
            "VoiceFileName": "20007020290",
            "CharacterMotions": [
                {
                    "slotNumber": 1,
                    "SpineId": 0,
                    "CharacterAppearanceType": 0,
                    "CharacterPosition": 2,
                    "CharacterLayerType": 1,
                    "SpineSize": 2
                },
                {
                    "slotNumber": 2,
                    "FacialExpressionMasterId": 72,
                    "BodyMotionMasterId": 13,
                    "LipSyncMasterId": 1,
                    "SpineId": 0,
                    "CharacterAppearanceType": 0,
                    "CharacterPosition": 4,
                    "CharacterLayerType": 1,
                    "SpineSize": 2
                }
            ],
            "SpeakerIconId": "509"
        },
        {
            "Id": 2000702038,
            "EpisodeMasterId": 2000702,
            "Order": 1,
            "GroupOrder": 34,
            "SpeakerName": "栞",
            "FontSize": 2,
            "Phrase": "ここに居て私の生活は保障されても、家族はそうじゃない。/n役を全然貰えない私は、仕送りできるほどのお給金じゃないし。",
            "VoiceFileName": "20007020300",
            "CharacterMotions": [
                {
                    "slotNumber": 1,
                    "SpineId": 0,
                    "CharacterAppearanceType": 0,
                    "CharacterPosition": 2,
                    "CharacterLayerType": 1,
                    "SpineSize": 2
                },
                {
                    "slotNumber": 2,
                    "FacialExpressionMasterId": 105,
                    "HeadMotionMasterId": 2,
                    "LipSyncMasterId": 1,
                    "SpineId": 0,
                    "CharacterAppearanceType": 0,
                    "CharacterPosition": 4,
                    "CharacterLayerType": 1,
                    "SpineSize": 2
                }
            ],
            "SpeakerIconId": "509"
        },
        {
            "Id": 2000702039,
            "EpisodeMasterId": 2000702,
            "Order": 1,
            "GroupOrder": 35,
            "SpeakerName": "暦",
            "FontSize": 2,
            "Phrase": "……そんな。これでお別れだなんて寂しいですわ。/nせっかく仲良くなれましたのに。",
            "VoiceFileName": "20007020310",
            "CharacterMotions": [
                {
                    "slotNumber": 1,
                    "FacialExpressionMasterId": 73,
                    "HeadMotionMasterId": 2,
                    "BodyMotionMasterId": 25,
                    "LipSyncMasterId": 4,
                    "SpineId": 0,
                    "CharacterAppearanceType": 0,
                    "CharacterPosition": 2,
                    "CharacterLayerType": 1,
                    "SpineSize": 2
                },
                {
                    "slotNumber": 2,
                    "SpineId": 0,
                    "CharacterAppearanceType": 0,
                    "CharacterPosition": 4,
                    "CharacterLayerType": 1,
                    "SpineSize": 2
                }
            ],
            "SpeakerIconId": "301"
        },
        {
            "Id": 2000702040,
            "EpisodeMasterId": 2000702,
            "Order": 1,
            "GroupOrder": 36,
            "SpeakerName": "暦",
            "FontSize": 2,
            "Phrase": "お家の事情が落ち着いたら、また銀河座に戻って来られないのですか？",
            "VoiceFileName": "20007020320",
            "CharacterMotions": [
                {
                    "slotNumber": 1,
                    "FacialExpressionMasterId": 400,
                    "BodyMotionMasterId": 7,
                    "LipSyncMasterId": 4,
                    "SpineId": 0,
                    "CharacterAppearanceType": 0,
                    "CharacterPosition": 2,
                    "CharacterLayerType": 1,
                    "SpineSize": 2
                },
                {
                    "slotNumber": 2,
                    "SpineId": 0,
                    "CharacterAppearanceType": 0,
                    "CharacterPosition": 4,
                    "CharacterLayerType": 1,
                    "SpineSize": 2
                }
            ],
            "SpeakerIconId": "301"
        },
        {
            "Id": 2000702041,
            "EpisodeMasterId": 2000702,
            "Order": 1,
            "GroupOrder": 37,
            "SpeakerName": "栞",
            "FontSize": 2,
            "Phrase": "どうだろう……。",
            "VoiceFileName": "20007020330",
            "CharacterMotions": [
                {
                    "slotNumber": 1,
                    "SpineId": 0,
                    "CharacterAppearanceType": 0,
                    "CharacterPosition": 2,
                    "CharacterLayerType": 1,
                    "SpineSize": 2
                },
                {
                    "slotNumber": 2,
                    "FacialExpressionMasterId": 72,
                    "BodyMotionMasterId": 20,
                    "LipSyncMasterId": 1,
                    "SpineId": 0,
                    "CharacterAppearanceType": 0,
                    "CharacterPosition": 4,
                    "CharacterLayerType": 1,
                    "SpineSize": 2
                }
            ],
            "SpeakerIconId": "509"
        },
        {
            "Id": 2000702042,
            "EpisodeMasterId": 2000702,
            "Order": 2,
            "GroupOrder": 37,
            "SpeakerName": "栞",
            "FontSize": 2,
            "Phrase": "うんって言いたいところだけど、難しいかな。",
            "VoiceFileName": "20007020331",
            "CharacterMotions": [
                {
                    "slotNumber": 1,
                    "SpineId": 0,
                    "CharacterAppearanceType": 0,
                    "CharacterPosition": 2,
                    "CharacterLayerType": 1,
                    "SpineSize": 2
                },
                {
                    "slotNumber": 2,
                    "FacialExpressionMasterId": 105,
                    "BodyMotionMasterId": 11,
                    "LipSyncMasterId": 1,
                    "SpineId": 0,
                    "CharacterAppearanceType": 0,
                    "CharacterPosition": 4,
                    "CharacterLayerType": 1,
                    "SpineSize": 2
                }
            ],
            "SpeakerIconId": "509"
        },
        {
            "Id": 2000702043,
            "EpisodeMasterId": 2000702,
            "Order": 1,
            "GroupOrder": 38,
            "SpeakerName": "栞",
            "FontSize": 2,
            "Phrase": "いつか共演しようって約束、守れなくてごめんね。",
            "VoiceFileName": "20007020340",
            "CharacterMotions": [
                {
                    "slotNumber": 1,
                    "SpineId": 0,
                    "CharacterAppearanceType": 0,
                    "CharacterPosition": 2,
                    "CharacterLayerType": 1,
                    "SpineSize": 2
                },
                {
                    "slotNumber": 2,
                    "FacialExpressionMasterId": 201,
                    "HeadMotionMasterId": 2,
                    "BodyMotionMasterId": 13,
                    "LipSyncMasterId": 1,
                    "SpineId": 0,
                    "CharacterAppearanceType": 0,
                    "CharacterPosition": 4,
                    "CharacterLayerType": 1,
                    "SpineSize": 2
                }
            ],
            "SpeakerIconId": "509"
        },
        {
            "Id": 2000702044,
            "EpisodeMasterId": 2000702,
            "Order": 1,
            "GroupOrder": 39,
            "SpeakerName": "暦",
            "FontSize": 2,
            "Phrase": "………。",
            "VoiceFileName": "20007020350",
            "CharacterMotions": [
                {
                    "slotNumber": 1,
                    "FacialExpressionMasterId": 400,
                    "BodyMotionMasterId": 4,
                    "LipSyncMasterId": 4,
                    "SpineId": 0,
                    "CharacterAppearanceType": 0,
                    "CharacterPosition": 2,
                    "CharacterLayerType": 1,
                    "SpineSize": 2
                },
                {
                    "slotNumber": 2,
                    "SpineId": 0,
                    "CharacterAppearanceType": 0,
                    "CharacterPosition": 4,
                    "CharacterLayerType": 1,
                    "SpineSize": 2
                }
            ],
            "SpeakerIconId": "301"
        },
        {
            "Id": 2000702045,
            "EpisodeMasterId": 2000702,
            "Order": 1,
            "GroupOrder": 40,
            "SpeakerName": "栞",
            "FontSize": 2,
            "Phrase": "辞めていく人が言うのもなんだけどさ、暦ちゃんは、/n銀河座に必要な人だって確信がある。",
            "VoiceFileName": "20007020360",
            "CharacterMotions": [
                {
                    "slotNumber": 1,
                    "FacialExpressionMasterId": 110,
                    "BodyMotionMasterId": 11,
                    "LipSyncMasterId": 4,
                    "SpineId": 50903,
                    "CharacterAppearanceType": 0,
                    "CharacterPosition": 3,
                    "CharacterLayerType": 1,
                    "SpineSize": 2
                }
            ],
            "SpeakerIconId": "509"
        },
        {
            "Id": 2000702046,
            "EpisodeMasterId": 2000702,
            "Order": 1,
            "GroupOrder": 41,
            "SpeakerName": "栞",
            "FontSize": 2,
            "Phrase": "だからここで頑張ってほしいな。",
            "VoiceFileName": "20007020370",
            "CharacterMotions": [
                {
                    "slotNumber": 1,
                    "FacialExpressionMasterId": 202,
                    "LipSyncMasterId": 1,
                    "SpineId": 0,
                    "CharacterAppearanceType": 0,
                    "CharacterPosition": 3,
                    "CharacterLayerType": 1,
                    "SpineSize": 2
                }
            ],
            "SpeakerIconId": "509"
        },
        {
            "Id": 2000702047,
            "EpisodeMasterId": 2000702,
            "Order": 1,
            "GroupOrder": 42,
            "SpeakerName": "栞",
            "FontSize": 2,
            "Phrase": "私はもう続けられないけど、銀河座の舞台を観て感動したから……。",
            "VoiceFileName": "20007020380",
            "CharacterMotions": [
                {
                    "slotNumber": 1,
                    "FacialExpressionMasterId": 402,
                    "BodyMotionMasterId": 25,
                    "LipSyncMasterId": 1,
                    "SpineId": 0,
                    "CharacterAppearanceType": 0,
                    "CharacterPosition": 3,
                    "CharacterLayerType": 1,
                    "SpineSize": 2
                }
            ],
            "SpeakerIconId": "509"
        },
        {
            "Id": 2000702048,
            "EpisodeMasterId": 2000702,
            "Order": 2,
            "GroupOrder": 42,
            "SpeakerName": "栞",
            "FontSize": 2,
            "Phrase": "私の分までいっぱい演じてほしい。",
            "VoiceFileName": "20007020381",
            "CharacterMotions": [
                {
                    "slotNumber": 1,
                    "FacialExpressionMasterId": 72,
                    "HeadMotionMasterId": 1,
                    "LipSyncMasterId": 1,
                    "SpineId": 0,
                    "CharacterAppearanceType": 0,
                    "CharacterPosition": 3,
                    "CharacterLayerType": 1,
                    "SpineSize": 2
                }
            ],
            "SpeakerIconId": "509"
        },
        {
            "Id": 2000702049,
            "EpisodeMasterId": 2000702,
            "Order": 1,
            "GroupOrder": 43,
            "SpeakerName": "暦",
            "FontSize": 2,
            "Phrase": "……はい。あなたの分まで、頑張りますから。",
            "VoiceFileName": "20007020390",
            "CharacterMotions": [
                {
                    "slotNumber": 1,
                    "FacialExpressionMasterId": 73,
                    "BodyMotionMasterId": 14,
                    "LipSyncMasterId": 4,
                    "SpineId": 30119,
                    "CharacterAppearanceType": 0,
                    "CharacterPosition": 3,
                    "CharacterLayerType": 1,
                    "SpineSize": 2
                }
            ],
            "SpeakerIconId": "301"
        },
        {
            "Id": 2000702050,
            "EpisodeMasterId": 2000702,
            "Order": 2,
            "GroupOrder": 43,
            "SpeakerName": "暦",
            "FontSize": 2,
            "Phrase": "公演案内も必ず送りますから、観に来てくださいね。",
            "VoiceFileName": "20007020391",
            "CharacterMotions": [
                {
                    "slotNumber": 1,
                    "FacialExpressionMasterId": 400,
                    "HeadMotionMasterId": 1,
                    "BodyMotionMasterId": 4,
                    "LipSyncMasterId": 4,
                    "SpineId": 0,
                    "CharacterAppearanceType": 0,
                    "CharacterPosition": 3,
                    "CharacterLayerType": 1,
                    "SpineSize": 2
                }
            ],
            "SpeakerIconId": "301"
        },
        {
            "Id": 2000702051,
            "EpisodeMasterId": 2000702,
            "Order": 1,
            "GroupOrder": 44,
            "SpeakerName": "栞",
            "FontSize": 2,
            "Phrase": "絶対行くよ。暦ちゃんの演技、大好きだから。/n楽しみに待ってるね。",
            "VoiceFileName": "20007020400",
            "CharacterMotions": [
                {
                    "slotNumber": 1,
                    "FacialExpressionMasterId": 201,
                    "BodyMotionMasterId": 20,
                    "LipSyncMasterId": 1,
                    "SpineId": 50903,
                    "CharacterAppearanceType": 0,
                    "CharacterPosition": 3,
                    "CharacterLayerType": 1,
                    "SpineSize": 2
                }
            ],
            "SpeakerIconId": "509"
        },
        {
            "Id": 2000702052,
            "EpisodeMasterId": 2000702,
            "Order": 1,
            "GroupOrder": 45,
            "SpeakerName": "暦",
            "FontSize": 2,
            "Phrase": "ええ。絶対ですよ。",
            "VoiceFileName": "20007020410",
            "CharacterMotions": [
                {
                    "slotNumber": 1,
                    "FacialExpressionMasterId": 105,
                    "HeadMotionMasterId": 1,
                    "BodyMotionMasterId": 4,
                    "LipSyncMasterId": 1,
                    "SpineId": 30119,
                    "CharacterAppearanceType": 0,
                    "CharacterPosition": 3,
                    "CharacterLayerType": 1,
                    "SpineSize": 2
                }
            ],
            "SpeakerIconId": "301"
        }
    ]
}